imagination_engine/__init__.py
imagination_engine/agent.py
imagination_engine/graph.py
imagination_engine/cli/__init__.py
imagination_engine/cli/test_commands.py
imagination_engine/utils/__init__.py
imagination_engine/utils/memory.py
imagination_engine/utils/start_end.py
imagination_engine/utils/tools.py
imagination_engine-0.1.2.dist-info/licenses/LICENSE
imagination_engine-0.1.2.dist-info/METADATA
imagination_engine-0.1.2.dist-info/WHEEL
imagination_engine-0.1.2.dist-info/entry_points.txt
imagination_engine-0.1.2.dist-info/top_level.txt
imagination_engine-0.1.2.dist-info/RECORD
